{
  "synthetic_vs_public": [
    {
      "topic": "Breadth vs concentration",
      "representation": 0.7128,
      "music": 0.697,
      "note": "One lane asks how broad the field looks; the other asks how tightly attention concentrates."
    },
    {
      "topic": "Parity vs dominance",
      "representation": 0.744,
      "music": 0.465,
      "note": "Parity is not the same question as market control, but both reveal where the center hardens."
    },
    {
      "topic": "Note-linked depth",
      "representation": null,
      "music": 0.0,
      "note": "The music lane can now report how much of the catalog is connected to score-level evidence."
    }
  ]
}